Workbook

Sheet Movimientos
A1: Reporte de movimientos de inventario
A2: Bodega Don Lucho
A3: Generado el 15/10/2026 11:50 · Del 01/10/2026 al 15/10/2026
A5: Fecha | B5: SKU | C5: Producto | D5: Tipo | E5: Motivo | F5: Cantidad | G5: Unidad | H5: Costo unit. (S/) | I5: Costo total (S/) | J5: Saldo | K5: Usuario | L5: Observaciones
A6: 46296.375 | B6: ARR-5KG | C6: Arroz extra Costeño 5 kg | D6: Entrada | E6: Compra | F6: 1 | G6: UND | H6: 18.5 | I6: =F6*H6 -> 18.5 | J6: 20 | K6: empleado | L6: Factura F001-0000
A7: 46296.583 | B7: AZU-1KG | C7: Azúcar rubia 1 kg | D7: Salida | E7: Venta | F7: 2 | G7: UND | H7: 4.1 | I7: =F7*H7 -> 8.2 | J7: 21 | K7: admin
A8: 46296.792 | B8: ACE-1L | C8: Aceite vegetal Primor 1 L | D8: Salida | E8: Venta | F8: 3 | G8: UND | H8: 9.9 | I8: =F8*H8 -> 29.7 | J8: 22 | K8: empleado
A9: 46297 | B9: LEC-400 | C9: Leche evaporada Gloria 400 g & lata <grande> | D9: Salida | E9: Merma | F9: 4 | G9: UND | H9: 3.2 | I9: =F9*H9 -> 12.8 | J9: 23 | K9: admin | L9: Producto vencido en almacén
A10: 46297.208 | B10: QUE-FRE | C10: Queso fresco | D10: Entrada | E10: Devolución de cliente | F10: 2.5 | G10: KG | H10: 22 | I10: =F10*H10 -> 55 | J10: 24 | K10: empleado | L10: Factura F001-0004
A11: 46297.417 | B11: CAB-14 | C11: Cable mellizo N.º 14 | D11: Salida | E11: Ajuste de inventario | F11: 2.5 | G11: M | H11: 2.3 | I11: =F11*H11 -> 5.75 | J11: 25 | K11: admin
A12: 46297.625 | B12: MAR-16 | C12: Martillo de uña 16 oz mango de fibra de vidrio antivibración | D12: Salida | E12: Venta | F12: 1 | G12: UND | H12: 24 | I12: =F12*H12 -> 24 | J12: 26 | K12: empleado
A13: 46297.833 | B13: DET-1KG | C13: Detergente Ariel 1 kg | D13: Salida | E13: Venta | F13: 2 | G13: UND | H13: 12.4 | I13: =F13*H13 -> 24.8 | J13: 27 | K13: admin
A14: 46298.042 | B14: ARR-5KG | C14: Arroz extra Costeño 5 kg | D14: Entrada | E14: Ajuste de inventario | F14: 3 | G14: UND | H14: 18.5 | I14: =F14*H14 -> 55.5 | J14: 28 | K14: empleado | L14: Factura F001-0008
A15: 46298.25 | B15: AZU-1KG | C15: Azúcar rubia 1 kg | D15: Salida | E15: Merma | F15: 4 | G15: UND | H15: 4.1 | I15: =F15*H15 -> 16.4 | J15: 20 | K15: admin | L15: Producto vencido en almacén
A16: 46298.458 | B16: ACE-1L | C16: Aceite vegetal Primor 1 L | D16: Salida | E16: Devolución a proveedor | F16: 5 | G16: UND | H16: 9.9 | I16: =F16*H16 -> 49.5 | J16: 21 | K16: empleado
A17: 46298.667 | B17: LEC-400 | C17: Leche evaporada Gloria 400 g & lata <grande> | D17: Salida | E17: Ajuste de inventario | F17: 6 | G17: UND | H17: 3.2 | I17: =F17*H17 -> 19.2 | J17: 22 | K17: admin
A18: 46298.875 | B18: QUE-FRE | C18: Queso fresco | D18: Entrada | E18: Compra | F18: 2.5 | G18: KG | H18: 22 | I18: =F18*H18 -> 55 | J18: 23 | K18: empleado | L18: Factura F001-0012
A19: 46299.083 | B19: CAB-14 | C19: Cable mellizo N.º 14 | D19: Salida | E19: Venta | F19: 2.5 | G19: M | H19: 2.3 | I19: =F19*H19 -> 5.75 | J19: 24 | K19: admin
A20: 46299.292 | B20: MAR-16 | C20: Martillo de uña 16 oz mango de fibra de vidrio antivibración | D20: Salida | E20: Venta | F20: 3 | G20: UND | H20: 24 | I20: =F20*H20 -> 72 | J20: 25 | K20: empleado
A21: 46299.5 | B21: DET-1KG | C21: Detergente Ariel 1 kg | D21: Salida | E21: Merma | F21: 4 | G21: UND | H21: 12.4 | I21: =F21*H21 -> 49.6 | J21: 26 | K21: admin | L21: Producto vencido en almacén
A22: 46299.708 | B22: ARR-5KG | C22: Arroz extra Costeño 5 kg | D22: Entrada | E22: Devolución de cliente | F22: 5 | G22: UND | H22: 18.5 | I22: =F22*H22 -> 92.5 | J22: 27 | K22: empleado | L22: Factura F001-0016
A23: 46299.917 | B23: AZU-1KG | C23: Azúcar rubia 1 kg | D23: Salida | E23: Ajuste de inventario | F23: 6 | G23: UND | H23: 4.1 | I23: =F23*H23 -> 24.6 | J23: 28 | K23: admin
A24: 46300.125 | B24: ACE-1L | C24: Aceite vegetal Primor 1 L | D24: Salida | E24: Venta | F24: 1 | G24: UND | H24: 9.9 | I24: =F24*H24 -> 9.9 | J24: 20 | K24: empleado
A25: 46300.333 | B25: LEC-400 | C25: Leche evaporada Gloria 400 g & lata <grande> | D25: Salida | E25: Venta | F25: 2 | G25: UND | H25: 3.2 | I25: =F25*H25 -> 6.4 | J25: 21 | K25: admin
A26: 46300.542 | B26: QUE-FRE | C26: Queso fresco | D26: Entrada | E26: Ajuste de inventario | F26: 2.5 | G26: KG | H26: 22 | I26: =F26*H26 -> 55 | J26: 22 | K26: empleado | L26: Factura F001-0020
A27: 46300.75 | B27: CAB-14 | C27: Cable mellizo N.º 14 | D27: Salida | E27: Merma | F27: 2.5 | G27: M | H27: 2.3 | I27: =F27*H27 -> 5.75 | J27: 23 | K27: admin | L27: Producto vencido en almacén
A28: 46300.958 | B28: MAR-16 | C28: Martillo de uña 16 oz mango de fibra de vidrio antivibración | D28: Salida | E28: Devolución a proveedor | F28: 5 | G28: UND | H28: 24 | I28: =F28*H28 -> 120 | J28: 24 | K28: empleado
A29: 46301.167 | B29: DET-1KG | C29: Detergente Ariel 1 kg | D29: Salida | E29: Ajuste de inventario | F29: 6 | G29: UND | H29: 12.4 | I29: =F29*H29 -> 74.4 | J29: 25 | K29: admin
A30: 46301.375 | B30: ARR-5KG | C30: Arroz extra Costeño 5 kg | D30: Entrada | E30: Compra | F30: 1 | G30: UND | H30: 18.5 | I30: =F30*H30 -> 18.5 | J30: 26 | K30: empleado | L30: Factura F001-0024
A31: 46301.583 | B31: AZU-1KG | C31: Azúcar rubia 1 kg | D31: Salida | E31: Venta | F31: 2 | G31: UND | H31: 4.1 | I31: =F31*H31 -> 8.2 | J31: 27 | K31: admin
A32: 46301.792 | B32: ACE-1L | C32: Aceite vegetal Primor 1 L | D32: Salida | E32: Venta | F32: 3 | G32: UND | H32: 9.9 | I32: =F32*H32 -> 29.7 | J32: 28 | K32: empleado
A33: 46302 | B33: LEC-400 | C33: Leche evaporada Gloria 400 g & lata <grande> | D33: Salida | E33: Merma | F33: 4 | G33: UND | H33: 3.2 | I33: =F33*H33 -> 12.8 | J33: 20 | K33: admin | L33: Producto vencido en almacén
A34: 46302.208 | B34: QUE-FRE | C34: Queso fresco | D34: Entrada | E34: Devolución de cliente | F34: 2.5 | G34: KG | H34: 22 | I34: =F34*H34 -> 55 | J34: 21 | K34: empleado | L34: Factura F001-0028
A35: 46302.417 | B35: CAB-14 | C35: Cable mellizo N.º 14 | D35: Salida | E35: Ajuste de inventario | F35: 2.5 | G35: M | H35: 2.3 | I35: =F35*H35 -> 5.75 | J35: 22 | K35: admin
A36: 46302.625 | B36: MAR-16 | C36: Martillo de uña 16 oz mango de fibra de vidrio antivibración | D36: Salida | E36: Venta | F36: 1 | G36: UND | H36: 24 | I36: =F36*H36 -> 24 | J36: 23 | K36: empleado
A37: 46302.833 | B37: DET-1KG | C37: Detergente Ariel 1 kg | D37: Salida | E37: Venta | F37: 2 | G37: UND | H37: 12.4 | I37: =F37*H37 -> 24.8 | J37: 24 | K37: admin
A38: 46303.042 | B38: ARR-5KG | C38: Arroz extra Costeño 5 kg | D38: Entrada | E38: Ajuste de inventario | F38: 3 | G38: UND | H38: 18.5 | I38: =F38*H38 -> 55.5 | J38: 25 | K38: empleado | L38: Factura F001-0032
A39: 46303.25 | B39: AZU-1KG | C39: Azúcar rubia 1 kg | D39: Salida | E39: Merma | F39: 4 | G39: UND | H39: 4.1 | I39: =F39*H39 -> 16.4 | J39: 26 | K39: admin | L39: Producto vencido en almacén
A40: 46303.458 | B40: ACE-1L | C40: Aceite vegetal Primor 1 L | D40: Salida | E40: Devolución a proveedor | F40: 5 | G40: UND | H40: 9.9 | I40: =F40*H40 -> 49.5 | J40: 27 | K40: empleado
A41: 46303.667 | B41: LEC-400 | C41: Leche evaporada Gloria 400 g & lata <grande> | D41: Salida | E41: Ajuste de inventario | F41: 6 | G41: UND | H41: 3.2 | I41: =F41*H41 -> 19.2 | J41: 28 | K41: admin
A42: 46303.875 | B42: QUE-FRE | C42: Queso fresco | D42: Entrada | E42: Compra | F42: 2.5 | G42: KG | H42: 22 | I42: =F42*H42 -> 55 | J42: 20 | K42: empleado | L42: Factura F001-0036
A43: 46304.083 | B43: CAB-14 | C43: Cable mellizo N.º 14 | D43: Salida | E43: Venta | F43: 2.5 | G43: M | H43: 2.3 | I43: =F43*H43 -> 5.75 | J43: 21 | K43: admin
A44: 46304.292 | B44: MAR-16 | C44: Martillo de uña 16 oz mango de fibra de vidrio antivibración | D44: Salida | E44: Venta | F44: 3 | G44: UND | H44: 24 | I44: =F44*H44 -> 72 | J44: 22 | K44: empleado
A45: 46304.5 | B45: DET-1KG | C45: Detergente Ariel 1 kg | D45: Salida | E45: Merma | F45: 4 | G45: UND | H45: 12.4 | I45: =F45*H45 -> 49.6 | J45: 23 | K45: admin | L45: Producto vencido en almacén
A46: 46304.708 | B46: ARR-5KG | C46: Arroz extra Costeño 5 kg | D46: Entrada | E46: Devolución de cliente | F46: 5 | G46: UND | H46: 18.5 | I46: =F46*H46 -> 92.5 | J46: 24 | K46: empleado | L46: Factura F001-0040
A47: 46304.917 | B47: AZU-1KG | C47: Azúcar rubia 1 kg | D47: Salida | E47: Ajuste de inventario | F47: 6 | G47: UND | H47: 4.1 | I47: =F47*H47 -> 24.6 | J47: 25 | K47: admin
A48: 46305.125 | B48: ACE-1L | C48: Aceite vegetal Primor 1 L | D48: Salida | E48: Venta | F48: 1 | G48: UND | H48: 9.9 | I48: =F48*H48 -> 9.9 | J48: 26 | K48: empleado
A49: 46305.333 | B49: LEC-400 | C49: Leche evaporada Gloria 400 g & lata <grande> | D49: Salida | E49: Venta | F49: 2 | G49: UND | H49: 3.2 | I49: =F49*H49 -> 6.4 | J49: 27 | K49: admin
A50: 46305.542 | B50: QUE-FRE | C50: Queso fresco | D50: Entrada | E50: Ajuste de inventario | F50: 2.5 | G50: KG | H50: 22 | I50: =F50*H50 -> 55 | J50: 28 | K50: empleado | L50: Factura F001-0044
A51: 46305.75 | B51: CAB-14 | C51: Cable mellizo N.º 14 | D51: Salida | E51: Merma | F51: 2.5 | G51: M | H51: 2.3 | I51: =F51*H51 -> 5.75 | J51: 20 | K51: admin | L51: Producto vencido en almacén
A52: 46305.958 | B52: MAR-16 | C52: Martillo de uña 16 oz mango de fibra de vidrio antivibración | D52: Salida | E52: Devolución a proveedor | F52: 5 | G52: UND | H52: 24 | I52: =F52*H52 -> 120 | J52: 21 | K52: empleado
A53: 46306.167 | B53: DET-1KG | C53: Detergente Ariel 1 kg | D53: Salida | E53: Ajuste de inventario | F53: 6 | G53: UND | H53: 12.4 | I53: =F53*H53 -> 74.4 | J53: 22 | K53: admin
A54: 46306.375 | B54: ARR-5KG | C54: Arroz extra Costeño 5 kg | D54: Entrada | E54: Compra | F54: 1 | G54: UND | H54: 18.5 | I54: =F54*H54 -> 18.5 | J54: 23 | K54: empleado | L54: Factura F001-0048
A55: 46306.583 | B55: AZU-1KG | C55: Azúcar rubia 1 kg | D55: Salida | E55: Venta | F55: 2 | G55: UND | H55: 4.1 | I55: =F55*H55 -> 8.2 | J55: 24 | K55: admin
A56: 46306.792 | B56: ACE-1L | C56: Aceite vegetal Primor 1 L | D56: Salida | E56: Venta | F56: 3 | G56: UND | H56: 9.9 | I56: =F56*H56 -> 29.7 | J56: 25 | K56: empleado
A57: 46307 | B57: LEC-400 | C57: Leche evaporada Gloria 400 g & lata <grande> | D57: Salida | E57: Merma | F57: 4 | G57: UND | H57: 3.2 | I57: =F57*H57 -> 12.8 | J57: 26 | K57: admin | L57: Producto vencido en almacén
A58: 46307.208 | B58: QUE-FRE | C58: Queso fresco | D58: Entrada | E58: Devolución de cliente | F58: 2.5 | G58: KG | H58: 22 | I58: =F58*H58 -> 55 | J58: 27 | K58: empleado | L58: Factura F001-0052
A59: 46307.417 | B59: CAB-14 | C59: Cable mellizo N.º 14 | D59: Salida | E59: Ajuste de inventario | F59: 2.5 | G59: M | H59: 2.3 | I59: =F59*H59 -> 5.75 | J59: 28 | K59: admin
A60: 46307.625 | B60: MAR-16 | C60: Martillo de uña 16 oz mango de fibra de vidrio antivibración | D60: Salida | E60: Venta | F60: 1 | G60: UND | H60: 24 | I60: =F60*H60 -> 24 | J60: 20 | K60: empleado
A61: 46307.833 | B61: DET-1KG | C61: Detergente Ariel 1 kg | D61: Salida | E61: Venta | F61: 2 | G61: UND | H61: 12.4 | I61: =F61*H61 -> 24.8 | J61: 21 | K61: admin
A62: 46308.042 | B62: ARR-5KG | C62: Arroz extra Costeño 5 kg | D62: Entrada | E62: Ajuste de inventario | F62: 3 | G62: UND | H62: 18.5 | I62: =F62*H62 -> 55.5 | J62: 22 | K62: empleado | L62: Factura F001-0056
A63: 46308.25 | B63: AZU-1KG | C63: Azúcar rubia 1 kg | D63: Salida | E63: Merma | F63: 4 | G63: UND | H63: 4.1 | I63: =F63*H63 -> 16.4 | J63: 23 | K63: admin | L63: Producto vencido en almacén
A64: 46308.458 | B64: ACE-1L | C64: Aceite vegetal Primor 1 L | D64: Salida | E64: Devolución a proveedor | F64: 5 | G64: UND | H64: 9.9 | I64: =F64*H64 -> 49.5 | J64: 24 | K64: empleado
A65: 46308.667 | B65: LEC-400 | C65: Leche evaporada Gloria 400 g & lata <grande> | D65: Salida | E65: Ajuste de inventario | F65: 6 | G65: UND | H65: 3.2 | I65: =F65*H65 -> 19.2 | J65: 25 | K65: admin
A66: 46308.875 | B66: QUE-FRE | C66: Queso fresco | D66: Entrada | E66: Compra | F66: 2.5 | G66: KG | H66: 22 | I66: =F66*H66 -> 55 | J66: 26 | K66: empleado | L66: Factura F001-0060
A67: 46309.083 | B67: CAB-14 | C67: Cable mellizo N.º 14 | D67: Salida | E67: Venta | F67: 2.5 | G67: M | H67: 2.3 | I67: =F67*H67 -> 5.75 | J67: 27 | K67: admin
A68: 46309.292 | B68: MAR-16 | C68: Martillo de uña 16 oz mango de fibra de vidrio antivibración | D68: Salida | E68: Venta | F68: 3 | G68: UND | H68: 24 | I68: =F68*H68 -> 72 | J68: 28 | K68: empleado
A69: 46309.5 | B69: DET-1KG | C69: Detergente Ariel 1 kg | D69: Salida | E69: Merma | F69: 4 | G69: UND | H69: 12.4 | I69: =F69*H69 -> 49.6 | J69: 20 | K69: admin | L69: Producto vencido en almacén
A70: 46309.708 | B70: ARR-5KG | C70: Arroz extra Costeño 5 kg | D70: Entrada | E70: Devolución de cliente | F70: 5 | G70: UND | H70: 18.5 | I70: =F70*H70 -> 92.5 | J70: 21 | K70: empleado | L70: Factura F001-0064
A71: 46309.917 | B71: AZU-1KG | C71: Azúcar rubia 1 kg | D71: Salida | E71: Ajuste de inventario | F71: 6 | G71: UND | H71: 4.1 | I71: =F71*H71 -> 24.6 | J71: 22 | K71: admin
A72: 46310.125 | B72: ACE-1L | C72: Aceite vegetal Primor 1 L | D72: Salida | E72: Venta | F72: 1 | G72: UND | H72: 9.9 | I72: =F72*H72 -> 9.9 | J72: 23 | K72: empleado
A73: 46310.333 | B73: LEC-400 | C73: Leche evaporada Gloria 400 g & lata <grande> | D73: Salida | E73: Venta | F73: 2 | G73: UND | H73: 3.2 | I73: =F73*H73 -> 6.4 | J73: 24 | K73: admin
A74: 46310.542 | B74: QUE-FRE | C74: Queso fresco | D74: Entrada | E74: Ajuste de inventario | F74: 2.5 | G74: KG | H74: 22 | I74: =F74*H74 -> 55 | J74: 25 | K74: empleado | L74: Factura F001-0068
A75: 46310.75 | B75: CAB-14 | C75: Cable mellizo N.º 14 | D75: Salida | E75: Merma | F75: 2.5 | G75: M | H75: 2.3 | I75: =F75*H75 -> 5.75 | J75: 26 | K75: admin | L75: Producto vencido en almacén
H77: Total entradas (S/) | I77: =SUMIF(D6:D75,"Entrada",I6:I75) -> 994.5
H78: Total salidas (S/) | I78: =SUMIF(D6:D75,"Salida",I6:I75) -> 1481.85

Sheet Resumen
A1: Resumen por motivo
A2: Bodega Don Lucho
A3: Generado el 15/10/2026 11:50 · Del 01/10/2026 al 15/10/2026
A5: Tipo | B5: Motivo | C5: N.º de movimientos | D5: Valor a costo (S/)
A6: Entrada | B6: Compra | C6: =COUNTIFS(Movimientos!$D$6:$D$75,"Entrada",Movimientos!$E$6:$E$75,"Compra") -> 6 | D6: =SUMIFS(Movimientos!$I$6:$I$75,Movimientos!$D$6:$D$75,"Entrada",Movimientos!$E$6:$E$75,"Compra") -> 220.5
A7: Entrada | B7: Devolución de cliente | C7: =COUNTIFS(Movimientos!$D$6:$D$75,"Entrada",Movimientos!$E$6:$E$75,"Devolución de cliente") -> 6 | D7: =SUMIFS(Movimientos!$I$6:$I$75,Movimientos!$D$6:$D$75,"Entrada",Movimientos!$E$6:$E$75,"Devolución de cliente") -> 442.5
A8: Entrada | B8: Ajuste de inventario | C8: =COUNTIFS(Movimientos!$D$6:$D$75,"Entrada",Movimientos!$E$6:$E$75,"Ajuste de inventario") -> 6 | D8: =SUMIFS(Movimientos!$I$6:$I$75,Movimientos!$D$6:$D$75,"Entrada",Movimientos!$E$6:$E$75,"Ajuste de inventario") -> 331.5
A9: Salida | B9: Venta | C9: =COUNTIFS(Movimientos!$D$6:$D$75,"Salida",Movimientos!$E$6:$E$75,"Venta") -> 24 | D9: =SUMIFS(Movimientos!$I$6:$I$75,Movimientos!$D$6:$D$75,"Salida",Movimientos!$E$6:$E$75,"Venta") -> 542.25
A10: Salida | B10: Merma | C10: =COUNTIFS(Movimientos!$D$6:$D$75,"Salida",Movimientos!$E$6:$E$75,"Merma") -> 12 | D10: =SUMIFS(Movimientos!$I$6:$I$75,Movimientos!$D$6:$D$75,"Salida",Movimientos!$E$6:$E$75,"Merma") -> 253.65
A11: Salida | B11: Devolución a proveedor | C11: =COUNTIFS(Movimientos!$D$6:$D$75,"Salida",Movimientos!$E$6:$E$75,"Devolución a proveedor") -> 5 | D11: =SUMIFS(Movimientos!$I$6:$I$75,Movimientos!$D$6:$D$75,"Salida",Movimientos!$E$6:$E$75,"Devolución a proveedor") -> 388.5
A12: Salida | B12: Ajuste de inventario | C12: =COUNTIFS(Movimientos!$D$6:$D$75,"Salida",Movimientos!$E$6:$E$75,"Ajuste de inventario") -> 11 | D12: =SUMIFS(Movimientos!$I$6:$I$75,Movimientos!$D$6:$D$75,"Salida",Movimientos!$E$6:$E$75,"Ajuste de inventario") -> 297.45
B13: Total | C13: =SUM(C6:C12) -> 70 | D13: =SUM(D6:D12) -> 2476.35
